anarcii/__init__.py
anarcii/classifii/__init__.py
anarcii/classifii/classifii.pt
anarcii/classifii/model.py
anarcii/classifii/params.json
anarcii/cli.py
anarcii/inference/__init__.py
anarcii/inference/model.py
anarcii/inference/model_loader.py
anarcii/inference/model_runner.py
anarcii/inference/utils.py
anarcii/inference/window_selector.py
anarcii/input_data_processing/__init__.py
anarcii/input_data_processing/sequences.py
anarcii/input_data_processing/tokeniser.py
anarcii/input_data_processing/utils.py
anarcii/models/__init__.py
anarcii/models/antibody/antibody_4_1_128_512.json
anarcii/models/antibody/antibody_4_1_128_512.pt
anarcii/models/antibody/antibody_4_2_128_512.json
anarcii/models/antibody/antibody_4_2_128_512.pt
anarcii/models/shark/shark_4_2_128_512.json
anarcii/models/shark/shark_4_2_128_512.pt
anarcii/models/tcr/tcr_4_1_128_512.json
anarcii/models/tcr/tcr_4_1_128_512.pt
anarcii/models/tcr/tcr_4_2_128_512.json
anarcii/models/tcr/tcr_4_2_128_512.pt
anarcii/output_data_processing/__init__.py
anarcii/output_data_processing/convert_to_legacy_format.py
anarcii/output_data_processing/scheme_specific_function.py
anarcii/output_data_processing/schemes.py
anarcii/output_data_processing/schemes_constants.py
anarcii/output_data_processing/schemes_utils.py
anarcii/pipeline/__init__.py
anarcii/pipeline/configuration.py
anarcii/pipeline/constants.py
anarcii/utils/__init__.py
anarcii-2.0.5.dist-info/licenses/LICENCE
anarcii-2.0.5.dist-info/WHEEL
anarcii-2.0.5.dist-info/entry_points.txt
anarcii-2.0.5.dist-info/METADATA
anarcii-2.0.5.dist-info/RECORD
