Metadata-Version: 2.4
Name: anarcii
Version: 2.0.5
Summary: A language model suite for numbering antigen receptor sequences.
Author: Alexander Greenshields Watson
Author-email: Alexander Greenshields Watson <opig@stats.ox.ac.uk>
License-File: LICENCE
Requires-Dist: gemmi
Requires-Dist: msgpack
Requires-Dist: numpy
Requires-Dist: psutil
Requires-Dist: sortedcontainers
Requires-Dist: torch
